yugioh/__init__.py
yugioh-0.0.26.dist-info/METADATA
yugioh-0.0.26.dist-info/WHEEL
yugioh-0.0.26.dist-info/top_level.txt
yugioh-0.0.26.dist-info/RECORD
