Metadata-Version: 2.1
Name: yugioh
Version: 0.0.26
Summary: Yu-Gi-Oh API Wrapper
Home-page: https://github.com/IThinkImOKAY/yugioh
Author: diogenesjunior
Author-email: diogenesjunior@protonmail.com
License: UNKNOWN
Keywords: Yu-Gi-Oh API
Platform: UNKNOWN
Requires-Dist: requests
